hilbertlib/__init__.py
hilbertlib/bot_development/__init__.py
hilbertlib/bot_development/chatbot.py
hilbertlib/bot_development/discord_bot.py
hilbertlib/bot_development/telegram_bot.py
hilbertlib/colors/__init__.py
hilbertlib/colors/colorconverter.py
hilbertlib/colors/colorgenerator.py
hilbertlib/colors/rgbmixer.py
hilbertlib/database/__init__.py
hilbertlib/database/hilbertbasicdb.py
hilbertlib/database/mysqlhelper.py
hilbertlib/database/sqlitehelper.py
hilbertlib/math_tools/__init__.py
hilbertlib/math_tools/matrix.py
hilbertlib/math_tools/polynomial_interpolator.py
hilbertlib/math_tools/probability.py
hilbertlib/math_tools/statistics.py
hilbertlib/math_tools/tensor.py
hilbertlib/math_tools/vectors.py
hilbertlib/web_utils/__init__.py
hilbertlib/web_utils/api_handler.py
hilbertlib/web_utils/html_parser.py
hilbertlib/web_utils/http_client.py
hilbertlib/web_utils/proxy_manager.py
hilbertlib/web_utils/rate_limiter.py
hilbertlib/web_utils/url_utils.py
hilbertlib/web_utils/web_scraper.py
hilbertlib/web_utils/webhook.py
hilbertlib-6.19.25.2.dist-info/LICENSE
hilbertlib-6.19.25.2.dist-info/METADATA
hilbertlib-6.19.25.2.dist-info/WHEEL
hilbertlib-6.19.25.2.dist-info/top_level.txt
hilbertlib-6.19.25.2.dist-info/RECORD
