Metadata-Version: 2.1
Name: hilbertlib
Version: 6.19.25.2
Summary: HilbertLib is a Python library providing modular tools for bot development, mathematical operations, web utilities, color manipulation, and database management.
Home-page: https://github.com/Synthfax/HilbertLib
Author: Synthfax
Author-email: synthfax@gmail.com
License: MIT
Classifier: Programming Language :: Python :: 3
Classifier: Operating System :: OS Independent
Classifier: License :: OSI Approved :: MIT License
Requires-Python: >=3.7
License-File: LICENSE
Requires-Dist: python-telegram-bot
Requires-Dist: discord.py
Requires-Dist: rapidfuzz
Requires-Dist: mysql-connector-python
